instructionkit/__init__.py
instructionkit/__main__.py
instructionkit/ai_tools/__init__.py
instructionkit/ai_tools/base.py
instructionkit/ai_tools/claude.py
instructionkit/ai_tools/copilot.py
instructionkit/ai_tools/cursor.py
instructionkit/ai_tools/detector.py
instructionkit/ai_tools/winsurf.py
instructionkit/cli/__init__.py
instructionkit/cli/delete.py
instructionkit/cli/download.py
instructionkit/cli/install.py
instructionkit/cli/install_new.py
instructionkit/cli/list.py
instructionkit/cli/main.py
instructionkit/cli/template.py
instructionkit/cli/template_backup.py
instructionkit/cli/template_init.py
instructionkit/cli/template_install.py
instructionkit/cli/template_list.py
instructionkit/cli/template_uninstall.py
instructionkit/cli/template_update.py
instructionkit/cli/template_validate.py
instructionkit/cli/tools.py
instructionkit/cli/uninstall.py
instructionkit/cli/update.py
instructionkit/core/__init__.py
instructionkit/core/checksum.py
instructionkit/core/conflict_resolution.py
instructionkit/core/git_operations.py
instructionkit/core/models.py
instructionkit/core/repository.py
instructionkit/core/template_manifest.py
instructionkit/storage/__init__.py
instructionkit/storage/library.py
instructionkit/storage/template_library.py
instructionkit/storage/template_tracker.py
instructionkit/storage/tracker.py
instructionkit/tui/__init__.py
instructionkit/tui/installer.py
instructionkit/utils/__init__.py
instructionkit/utils/backup.py
instructionkit/utils/git_helpers.py
instructionkit/utils/logging.py
instructionkit/utils/namespace.py
instructionkit/utils/paths.py
instructionkit/utils/project.py
instructionkit/utils/ui.py
instructionkit/utils/validation.py
instructionkit-0.4.0.dist-info/LICENSE
instructionkit-0.4.0.dist-info/METADATA
instructionkit-0.4.0.dist-info/WHEEL
instructionkit-0.4.0.dist-info/entry_points.txt
instructionkit-0.4.0.dist-info/top_level.txt
instructionkit-0.4.0.dist-info/RECORD
