Metadata-Version: 2.1
Name: instructionkit
Version: 0.4.0
Summary: CLI tool for managing AI coding tool instructions
Author-email: Troy Larson <troy@calvinware.com>
License: MIT License
Project-URL: Homepage, https://github.com/instructionkit/instructionkit
Project-URL: Documentation, https://github.com/instructionkit/instructionkit#readme
Project-URL: Repository, https://github.com/instructionkit/instructionkit
Project-URL: Issues, https://github.com/instructionkit/instructionkit/issues
Keywords: cli,ai,instructions,cursor,copilot,claude
Classifier: Development Status :: 3 - Alpha
Classifier: Intended Audience :: Developers
Classifier: Programming Language :: Python :: 3
Classifier: Programming Language :: Python :: 3.10
Classifier: Programming Language :: Python :: 3.11
Classifier: Programming Language :: Python :: 3.12
Classifier: Programming Language :: Python :: 3.13
Requires-Python: >=3.10
License-File: LICENSE
Requires-Dist: typer[all]>=0.9.0
Requires-Dist: rich>=13.0.0
Requires-Dist: pyyaml>=6.0
Requires-Dist: textual>=0.41.0
Requires-Dist: GitPython>=3.1.45
Provides-Extra: dev
Requires-Dist: pytest>=7.0.0; extra == "dev"
Requires-Dist: pytest-cov>=4.0.0; extra == "dev"
Requires-Dist: black>=23.0.0; extra == "dev"
Requires-Dist: mypy>=1.0.0; extra == "dev"
Requires-Dist: ruff>=0.1.0; extra == "dev"
Requires-Dist: invoke>=2.0.0; extra == "dev"
Requires-Dist: build>=1.2.1; extra == "dev"
Requires-Dist: twine>=5.0.0; extra == "dev"
Requires-Dist: types-PyYAML>=6.0.12.20240808; extra == "dev"
